setup.py
django_ios_notification.egg-info/PKG-INFO
django_ios_notification.egg-info/SOURCES.txt
django_ios_notification.egg-info/dependency_links.txt
django_ios_notification.egg-info/top_level.txt
ios_notification/__init__.py
ios_notification/models.py
ios_notification/tests.py
ios_notification/views.py