Metadata-Version: 1.0
Name: django-ios-notification
Version: 1.0.4
Summary: A Django Application for contacting the Apple Push Service and maintaining a list of iOS devices.
Home-page: https://github.com/matheussl/django-ios-notification
Author: Matheus Lima
Author-email: matheus.se@gmail.com
License: Apache License 2.0
Keywords: django ios notification push
Platform: UNKNOWN
